setup.cfg
setup.py
MarkCaptcha.egg-info/PKG-INFO
MarkCaptcha.egg-info/SOURCES.txt
MarkCaptcha.egg-info/dependency_links.txt
MarkCaptcha.egg-info/entry_points.txt
MarkCaptcha.egg-info/requires.txt
MarkCaptcha.egg-info/top_level.txt
markcaptcha/__init__.py
markcaptcha/__main__.py
markcaptcha/tasks.py
markcaptcha/widgets.py