Metadata-Version: 1.1
Name: MarkCaptcha
Version: 1.0
Summary: MarkCaptcha: 验证码样本标注工具
Home-page: https://github.com/holymonk/MarkCaptcha
Author: Monk
Author-email: manwu91@gmail.com
License: MIT
Keywords: Captcha Training
Platform: any
Classifier: Operating System :: OS Independent
Classifier: Natural Language :: Chinese (Simplified)
Classifier: Programming Language :: Python :: 3
Classifier: Topic :: Utilities
